rhllasag/__init__.py
rhllasag/__main__.py
rhllasag-1.0.0.dist-info/METADATA
rhllasag-1.0.0.dist-info/WHEEL
rhllasag-1.0.0.dist-info/top_level.txt
rhllasag-1.0.0.dist-info/RECORD
