Metadata-Version: 2.4
Name: rhllasag
Version: 1.0.0
Summary: A Python package template.
Author-email: Raúl Rosero <raul.hllasag@gmail.com>
License-Expression: MIT
Requires-Python: >=3.8
Provides-Extra: dev-requirements
Requires-Dist: dev-requirements.txt; extra == "dev-requirements"
